Workbook
Name aporte: #REF!
Name patrimonio: #REF!
Name qtd_anos: #REF!
Name rendimento_carteira: #REF!
Name salario: #REF!
Name sugestao_investimento: #REF!
Name taxa_mensal: #REF!

Sheet APP JV
B9: CONFIGURAÇÕES
B10: Salário | D10: 2000
B11: Rendimento Carteira | D11: 0.006
B12: Sugestão de Investimento (30%) | D12: =D10*30% -> 600
B14: INVESTIMENTO MENSAL
B15: Quanto investir por mês ? | D15: 200
B16: Por Quantos Anos ? | D16: 5
B17: Taxa de Rendimento mensal ? | D17: 0.0108
B18: Patrimônio acumulado ? | D18: =FV($D$17,D16*12,-$D$15) -> 16760.804
B19: Dividendos Mensais ? | D19: =D18*D11 -> 100.56482
B22: Cenários | D22: Dividendo
A23: 2 | B23: Quanto em 2 Anos ? | C23: =FV($D$17,$A23*12,-$D$15) -> 5446.1727 | D23: =C23*$D$11 -> 32.677036
A24: 5 | B24: Quanto em 5 Anos ? | C24: =FV($D$17,$A24*12,-$D$15) -> 16760.804 | D24: =C24*$D$11 -> 100.56482
A25: 10 | B25: Quanto em 10 Anos ? | C25: =FV($D$17,$A25*12,-$D$15) -> 48691.533 | D25: =C25*$D$11 -> 292.1492
A26: 20 | B26: Quanto em 20 Anos ? | C26: =FV($D$17,$A26*12,-$D$15) -> 225409.8 | D26: =C26*$D$11 -> 1352.4588
A27: 30 | B27: Quanto em 30 Anos ? | C27: =FV($D$17,$A27*12,-$D$15) -> 866780.96 | D27: =C27*$D$11 -> 5200.6858
B29: PERFIL | C29: Agressivo
B30: VALOR A SER INVESTIDO POR MÊS | C30: =D15 -> 200
B32: TIPO DE FII | C32: Percentual Sugerido | D32: Valores
B33: PAPEL | C33: =VLOOKUP($C$29&"-"&B33,Planilha2!$A:$D,4,FALSE) -> 0.5 | D33: =C33*$C$30 -> 100
B34: TIJOLO | C34: =VLOOKUP($C$29&"-"&B34,Planilha2!$A:$D,4,FALSE) -> 0.1 | D34: =C34*$C$30 -> 20
B35: HÍBRIDOS | C35: =VLOOKUP($C$29&"-"&B35,Planilha2!$A:$D,4,FALSE) -> 0.05 | D35: =C35*$C$30 -> 10
B36: FOFs | C36: =VLOOKUP($C$29&"-"&B36,Planilha2!$A:$D,4,FALSE) -> 0.05 | D36: =C36*$C$30 -> 10
B37: DESENVOLVIMENTO | C37: =VLOOKUP($C$29&"-"&B37,Planilha2!$A:$D,4,FALSE) -> 0.2 | D37: =C37*$C$30 -> 40
B38: HOTELARIAS | C38: =VLOOKUP($C$29&"-"&B38,Planilha2!$A:$D,4,FALSE) -> 0.1 | D38: =C38*$C$30 -> 20
D39: =SUM(D33:D38) -> 200

Sheet Planilha2
A2: CHAVE | B2: PERFIL | C2: TIPO DE FII | D2: %
A3: =B3&"-"&C3 -> Conservador-PAPEL | B3: Conservador | C3: PAPEL | D3: 0.3 | H3: %
A4: =B4&"-"&C4 -> Conservador-TIJOLO | B4: Conservador | C4: TIJOLO | D4: 0.5 | G4: Moderado-TIJOLO | H4: =VLOOKUP(G4,$A:$D,4,FALSE) -> 0.35
A5: =B5&"-"&C5 -> Conservador-HÍBRIDOS | B5: Conservador | C5: HÍBRIDOS | D5: 0.1
A6: =B6&"-"&C6 -> Conservador-FOFs | B6: Conservador | C6: FOFs | D6: 0.1
A7: =B7&"-"&C7 -> Conservador-DESENVOLVIMENTO | B7: Conservador | C7: DESENVOLVIMENTO | D7: 0
A8: =B8&"-"&C8 -> Conservador-HOTELARIAS | B8: Conservador | C8: HOTELARIAS | D8: 0
A9: =B9&"-"&C9 -> Moderado-PAPEL | B9: Moderado | C9: PAPEL | D9: 0.32
A10: =B10&"-"&C10 -> Moderado-TIJOLO | B10: Moderado | C10: TIJOLO | D10: 0.35
A11: =B11&"-"&C11 -> Moderado-HÍBRIDOS | B11: Moderado | C11: HÍBRIDOS | D11: 0.08
A12: =B12&"-"&C12 -> Moderado-FOFs | B12: Moderado | C12: FOFs | D12: 0.05
A13: =B13&"-"&C13 -> Moderado-DESENVOLVIMENTO | B13: Moderado | C13: DESENVOLVIMENTO | D13: 0.1
A14: =B14&"-"&C14 -> Moderado-HOTELARIAS | B14: Moderado | C14: HOTELARIAS | D14: 0.1
A15: =B15&"-"&C15 -> Agressivo-PAPEL | B15: Agressivo | C15: PAPEL | D15: 0.5
A16: =B16&"-"&C16 -> Agressivo-TIJOLO | B16: Agressivo | C16: TIJOLO | D16: 0.1
... A20: =B20&"-"&C20 -> Agressivo-HOTELARIAS | B20: Agressivo | C20: HOTELARIAS | D20: 0.1
